do_gradientai/__init__.py
do_gradientai/_base_client.py
do_gradientai/_client.py
do_gradientai/_compat.py
do_gradientai/_constants.py
do_gradientai/_exceptions.py
do_gradientai/_files.py
do_gradientai/_models.py
do_gradientai/_qs.py
do_gradientai/_resource.py
do_gradientai/_response.py
do_gradientai/_streaming.py
do_gradientai/_types.py
do_gradientai/_version.py
do_gradientai/py.typed
do_gradientai/_utils/__init__.py
do_gradientai/_utils/_logs.py
do_gradientai/_utils/_proxy.py
do_gradientai/_utils/_reflection.py
do_gradientai/_utils/_resources_proxy.py
do_gradientai/_utils/_streams.py
do_gradientai/_utils/_sync.py
do_gradientai/_utils/_transform.py
do_gradientai/_utils/_typing.py
do_gradientai/_utils/_utils.py
do_gradientai/lib/.keep
do_gradientai/resources/__init__.py
do_gradientai/resources/regions.py
do_gradientai/resources/agents/__init__.py
do_gradientai/resources/agents/agents.py
do_gradientai/resources/agents/api_keys.py
do_gradientai/resources/agents/evaluation_datasets.py
do_gradientai/resources/agents/evaluation_runs.py
do_gradientai/resources/agents/evaluation_test_cases.py
do_gradientai/resources/agents/functions.py
do_gradientai/resources/agents/knowledge_bases.py
do_gradientai/resources/agents/routes.py
do_gradientai/resources/agents/versions.py
do_gradientai/resources/agents/chat/__init__.py
do_gradientai/resources/agents/chat/chat.py
do_gradientai/resources/agents/chat/completions.py
do_gradientai/resources/agents/evaluation_metrics/__init__.py
do_gradientai/resources/agents/evaluation_metrics/evaluation_metrics.py
do_gradientai/resources/agents/evaluation_metrics/models.py
do_gradientai/resources/agents/evaluation_metrics/anthropic/__init__.py
do_gradientai/resources/agents/evaluation_metrics/anthropic/anthropic.py
do_gradientai/resources/agents/evaluation_metrics/anthropic/keys.py
do_gradientai/resources/agents/evaluation_metrics/openai/__init__.py
do_gradientai/resources/agents/evaluation_metrics/openai/keys.py
do_gradientai-0.1.0b4.dist-info/METADATA
do_gradientai-0.1.0b4.dist-info/WHEEL
do_gradientai-0.1.0b4.dist-info/licenses/LICENSE
do_gradientai-0.1.0b4.dist-info/RECORD
